{"type":"FeatureCollection","crs":{"type":"name","properties":{"name":"EPSG:4326"}},"features":[{"type":"Feature","id":0,"geometry":{"type":"Point","coordinates":[-72.11391834799997,-15.717446185999961]},"properties":{"FID":0,"N°":415,"CUI":"2436559","FECHA":1759190400000,"JERARQUIA":"RVV","COD_RUTA":"R","RUTA_RECLA":"-","IDDPTO":"04","IDPROV":"0405","DPTO":"AREQUIPA","PROV":"CAYLLOMA","NOM_PUENTE":"SAJARHUA","HITO_KM":"-","LONGITUD_m":30,"CLASE":"DEFINITIVO","CONDICION":"MALO","N_CARRILES":2,"A_CALZADA":7.2000000000000002,"N_CONVENIO":"-","INVENTARIO":"-","ZONA_UTM":"18S","FUENTE":"GIE","CARTERA":"RCC","COMENTARIO":"LEY Nº 30556 RECONSTRUCCIÓN CON CAMBIOS, EXIME A FIRMA DE CONVENIOS CON LOS GOBIERNO LOCALES Y REGIONALES","A_F_A_PCTJ":"1.58 %","CUI_":2436559,"CUI_12":2436559,"NOMBRE_COR":"REHABILITACIÓN DE PUENTE SAJARHUA Y ACCESOS (REHABILITACIÓN DE PUENTES PAQUETE 5 – HUANCAVELICA-AYACUCHO-AREQUIPA 2)","COSTO":19368561.469999999,"NOMBRE_LAR":"REHABILITACIÓN DE PUENTE SAJARHUA Y ACCESOS (REHABILITACIÓN DE PUENTES PAQUETE 5 – HUANCAVELICA-AYACUCHO-AREQUIPA 2)","PMI":"PMI DEL SECTOR","PMI_AACTUA":267927}}]}